shuup_onboarding/__init__.py
shuup_onboarding/apps.py
shuup_onboarding/base.py
shuup_onboarding/middleware.py
shuup_onboarding/onboard.py
shuup_onboarding/settings.py
shuup_onboarding/storage.py
shuup_onboarding/urls.py
shuup_onboarding/admin/__init__.py
shuup_onboarding/admin/views.py
shuup_onboarding/templates/shuup_onboarding/admin/macros.jinja
shuup_onboarding/templates/shuup_onboarding/admin/onboard.jinja
shuup_onboarding_tests/__init__.py
shuup_onboarding_tests/settings.py
shuup_onboarding_tests/test_app.py
shuup_onboarding-1.0.0.dist-info/LICENSE
shuup_onboarding-1.0.0.dist-info/METADATA
shuup_onboarding-1.0.0.dist-info/WHEEL
shuup_onboarding-1.0.0.dist-info/entry_points.txt
shuup_onboarding-1.0.0.dist-info/top_level.txt
shuup_onboarding-1.0.0.dist-info/RECORD
