Metadata-Version: 2.1
Name: shuup-onboarding
Version: 1.0.0
Summary: UNKNOWN
Home-page: UNKNOWN
License: UNKNOWN
Platform: UNKNOWN
Requires-Dist: shuup
